pyvista_imgui/__init__.py
pyvista_imgui/_backend_imgui_bundle.py
pyvista_imgui/_backend_pyimgui.py
pyvista_imgui/_version.py
pyvista_imgui/imgui_render_window.py
pyvista_imgui/interactor_style_pivot.py
pyvista_imgui/plotting.py
pyvista_imgui/texture_render_window.py
pyvista_imgui-0.5.0.dist-info/LICENSE
pyvista_imgui-0.5.0.dist-info/METADATA
pyvista_imgui-0.5.0.dist-info/WHEEL
pyvista_imgui-0.5.0.dist-info/top_level.txt
pyvista_imgui-0.5.0.dist-info/RECORD
