Metadata-Version: 2.1
Name: pyvista-imgui
Version: 0.5.0
Summary: Pyvista imgui integration
Author-email: Felix Igelbrink <felix.igelbrink@dfki.de>
License: MIT
Project-URL: Bug Tracker, https://github.com/mortacious/pyvista-imgui/issues
Project-URL: Source Code, https://github.com/mortacious/pyvista-imgui
Keywords: vtk,imgui,plotting
Classifier: Development Status :: 4 - Beta
Classifier: Programming Language :: Python :: 3.8
Classifier: Programming Language :: Python :: 3.9
Classifier: Programming Language :: Python :: 3.10
Classifier: Programming Language :: Python :: 3.11
Classifier: Topic :: Scientific/Engineering :: Information Analysis
Classifier: License :: OSI Approved :: MIT License
Classifier: Operating System :: Microsoft :: Windows
Classifier: Operating System :: POSIX
Classifier: Operating System :: MacOS
Requires-Python: >=3.8
License-File: LICENSE
Requires-Dist: pyvista >=0.39
Requires-Dist: vtk
Requires-Dist: importlib-metadata ; python_version > "3.8"
Provides-Extra: imgui
Requires-Dist: imgui[glfw] ; extra == 'imgui'
Provides-Extra: imgui-bundle
Requires-Dist: imgui-bundle ; extra == 'imgui-bundle'
